{"homeUrl":"http:\/\/www.fkzww.com","enable":true,"authorId":"f6c7b3b2e24e10542d9fb490b46c4752","bookDetail":{"forGetMethod":true,"parser":{"coverUrl":"div[@id=CrbtlBookImg].img.@src","desc":"div[@id=CrbsSum]","lastUpdateDate":"ul[@class=h1][0].li[5]"},"params":{},"url":"@dyn:u=source.helpId; check(!u, return nil); format('http:\/\/www.fkzww.com%@', u)"},"bookWorld":{},"httpConfigs":{"headers":{},"customFormatValueParam":"JxdSecuritySub.Gb2312Encoded:value","useCookies":true},"chapterDetail":{"forGetMethod":true,"parser":{"content":"div[@id=BookTextt]"},"params":{}},"weight":1,"priorityEncoding":4,"needSupportDynTask":true,"sourceDetail":{"forGetMethod":true,"parser":{"lastUpdateDate":"div[@id=TextInfo]","_1":{"_list":"div[@id=BookText].li","title":"a","url":"@href"}},"params":{}},"lastModifyTime":"2019-03-09 02:37:01","responseType":4,"searchBook":{"forGetMethod":false,"parser":{"_1":{"dirURL":"a[4].@href#\\d{1,10}\\.shtml @=>List.shtml","helpId":"a[0].@href"},"author":"a[1]","bookName":"b","_list":"div[@id=CListTitle]","typeText":"a[2]"},"params":{"button":"快速搜索","SearchClass":"1","SearchKey":"%@"},"url":"http:\/\/www.fkzww.com\/Book\/Search.aspx"},"name":"疯狂中文网"}